[
	{
		"Devices": "ASUS TEST ",
		"Models": "[TEST]",
		"Platform": "Qualcomm",
		"Conn": "Auto",
		"Broom": "EDL"
	},
	{
		"Devices": "ASUS ASUS Live L1 ",
		"Models": "[X00RD]",
		"Platform": "Qualcomm",
		"Conn": "Auto",
		"Broom": "EDL"
	},
	{
		"Devices": "ASUS ASUS M1 PRO ",
		"Models": "[ZQL1650]",
		"Platform": "Qualcomm",
		"Conn": "Auto",
		"Broom": "EDL"
	},
	{
		"Devices": "ASUS ASUS M2 PRO ",
		"Models": "[ZQL1820P]",
		"Platform": "Qualcomm",
		"Conn": "Auto",
		"Broom": "EDL"
	},
	{
		"Devices": "Asus Zenfone 3 Max",
		"Models": "ZC520TL X008D",
		"Platform": "MT6737",
		"Conn": "Auto",
		"Broom": "Brom"
	},
	{
		"Devices": "Asus Zenfone 3s Max",
		"Models": "ZC521TL X00GD",
		"Platform": "MT6750",
		"Conn": "Auto",
		"Broom": "Brom"
	},
	{
		"Devices": "Asus Zenfone 4 Max",
		"Models": "ZB500TL X00KD",
		"Platform": "MT6737",
		"Conn": "Auto",
		"Broom": "Brom"
	},
	{
		"Devices": "Asus Zenfone 4 Max Plus",
		"Models": "ZC550TL X015D",
		"Platform": "MT6750",
		"Conn": "Auto",
		"Broom": "Brom"
	},
	{
		"Devices": "Asus Zenfone Max Plus M1",
		"Models": "ZB570TL X018DC",
		"Platform": "MT6750",
		"Conn": "Auto",
		"Broom": "Brom"
	}
]
